ndare/__init__.py
ndare/base/__init__.py
ndare-0.0.0.dist-info/LICENSE.txt
ndare-0.0.0.dist-info/WHEEL
ndare-0.0.0.dist-info/METADATA
ndare-0.0.0.dist-info/RECORD
